AUTHORS.rst
HISTORY.rst
LICENSE.txt
MANIFEST.in
README.md
requirements.txt
setup.py
frank/__init__.py
frank/constants.py
frank/default_parameters.json
frank/fit.py
frank/frank.mplstyle
frank/geometry.py
frank/hankel.py
frank/io.py
frank/make_figs.py
frank/parameter_descriptions.json
frank/plot.py
frank/radial_fitters.py
frank/tests.py
frank/utilities.py
frank_astro.egg-info/PKG-INFO
frank_astro.egg-info/SOURCES.txt
frank_astro.egg-info/dependency_links.txt
frank_astro.egg-info/requires.txt
frank_astro.egg-info/top_level.txt