Metadata-Version: 2.1
Name: frank-astro
Version: 1.1.0
Summary: Frankenstein, the flux reconstructor
Home-page: https://github.com/discsim/frank
Author: Richard Booth, Jeff Jennings, Marco Tazzari
Author-email: jmj51@ast.cam.ac.uk
License: GPLv3
Keywords: science,astronomy,interferometry
Platform: UNKNOWN
Classifier: Development Status :: 5 - Production/Stable
Classifier: Intended Audience :: Developers
Classifier: Intended Audience :: Science/Research
Classifier: Operating System :: OS Independent
Classifier: License :: OSI Approved :: GNU Lesser General Public License v3 (LGPLv3)
Classifier: Programming Language :: Python :: 3
Requires-Python: >=3
Provides-Extra: test
Provides-Extra: docs-build
